pudl_catalog/__init__.py
pudl_catalog/helpers.py
pudl_catalog/pudl_catalog.yaml
catalystcoop.pudl_catalog-2022.11.30.dist-info/LICENSE.txt
catalystcoop.pudl_catalog-2022.11.30.dist-info/METADATA
catalystcoop.pudl_catalog-2022.11.30.dist-info/WHEEL
catalystcoop.pudl_catalog-2022.11.30.dist-info/entry_points.txt
catalystcoop.pudl_catalog-2022.11.30.dist-info/top_level.txt
catalystcoop.pudl_catalog-2022.11.30.dist-info/RECORD
